[
  {
    "type": "mapgen",
    "om_terrain": [ "s_restaurant_coffee" ],
    "method": "json",
    "weight": 250,
    "object": {
      "fill_ter": "t_floor",
      "rows": [
        "_______,,,,,,,ss########",
        "______________ss#pppppp#",
        "______________ssspHTTHp#",
        "______________ssspppppp#",
        "______________ssspHppHp#",
        "_______,,,,,,,ssspTppTp#",
        "______________ssspHppHp#",
        "______________ssspppppp#",
        "______________ss#pHTTHp#",
        "______________ss#pppppp#",
        "_______,,,,,,,ss|-5555-|",
        "______________ss|.HTTH.|",
        "______________ss%......|",
        "______________ss+.....&|",
        "______________ss+......|",
        "ssssssssssssssss%....HH|",
        "|--555-555-555--|....TT|",
        "|..HTH.HTH.HTH.......TT|",
        "|....................HH|",
        "|......................|",
        "|-D---D---cWWcccxccxccc|",
        "|S==|==S|==============|",
        "|P==|==P|llSO==rrrrrSTe|",
        "|-------------L--------|"
      ],
      "terrain": {
        "D": [
          "t_door_c",
          "t_door_c",
          "t_door_b",
          "t_door_c",
          "t_door_c",
          "t_door_frame",
          "t_door_c",
          "t_door_c",
          "t_wall_wood",
          "t_door_c",
          "t_door_c",
          "t_wall_wood_chipped",
          "t_door_c",
          "t_door_c",
          "t_wall_wood_broken",
          "t_door_o",
          "t_door_o",
          "t_wall_log",
          "t_door_o",
          "t_door_o",
          "t_wall_log_chipped",
          "t_door_o",
          "t_door_o",
          "t_wall_log_broken"
        ],
        "L": [
          "t_door_c",
          "t_door_c",
          "t_door_b",
          "t_door_c",
          "t_door_c",
          "t_door_frame",
          "t_door_c",
          "t_door_c",
          "t_wall_wood",
          "t_door_c",
          "t_door_c",
          "t_wall_wood_chipped",
          "t_door_c",
          "t_door_c",
          "t_wall_wood_broken",
          "t_door_o",
          "t_door_o",
          "t_wall_log",
          "t_door_o",
          "t_door_o",
          "t_wall_log_chipped",
          "t_door_o",
          "t_door_o",
          "t_wall_log_broken"
        ],
        "+": [
          "t_door_glass_c",
          "t_door_glass_c",
          "t_door_frame",
          "t_door_glass_c",
          "t_door_glass_c",
          "t_wall_wood",
          "t_door_glass_c",
          "t_door_glass_c",
          "t_wall_wood_chipped",
          "t_door_glass_c",
          "t_door_glass_c",
          "t_wall_wood_broken",
          "t_door_glass_o",
          "t_door_glass_o",
          "t_wall_log",
          "t_door_glass_o",
          "t_door_glass_o",
          "t_wall_log_chipped",
          "t_door_glass_o",
          "t_door_glass_o",
          "t_wall_log_broken"
        ],
        "5": "t_wall_glass",
        "%": "t_wall_glass",
        ",": "t_pavement_y",
        "_": "t_pavement",
        "x": "t_console_broken",
        ".": "t_floor",
        "-": "t_wall",
        "|": "t_wall",
        "#": "t_shrub",
        "s": "t_sidewalk",
        "p": "t_concrete",
        "W": [ "t_fencegate_c", "t_fencegate_c", "t_fencegate_c", "t_fencegate_o" ],
        "=": "t_linoleum_white",
        "e": "t_linoleum_white",
        "T": "t_linoleum_white",
        "S": "t_linoleum_white",
        "c": "t_linoleum_white",
        "O": "t_linoleum_white",
        "P": "t_linoleum_white",
        "l": "t_linoleum_white",
        "r": "t_linoleum_white"
      },
      "furniture": {
        "r": [ "f_rack", "f_null", "f_null", "f_null", "f_null", "f_null", "f_null", "f_rack", "f_rubble", "f_rack" ],
        "l": [ "f_locker", "f_null", "f_null", "f_null", "f_null", "f_null", "f_null", "f_locker", "f_wreckage", "f_locker" ],
        "T": [ "f_table", "f_null", "f_null", "f_null", "f_null", "f_null", "f_null", "f_table", "f_rubble", "f_table" ],
        "S": [ "f_sink", "f_null", "f_null", "f_null", "f_null", "f_null", "f_null", "f_sink", "f_rubble", "f_sink" ],
        "e": [ "f_fridge", "f_null", "f_null", "f_null", "f_null", "f_null", "f_null", "f_fridge", "f_wreckage", "f_fridge" ],
        "O": [ "f_oven", "f_null", "f_null", "f_null", "f_null", "f_null", "f_null", "f_oven", "f_wreckage", "f_oven" ],
        "H": [ "f_chair", "f_null", "f_null", "f_null", "f_null", "f_null", "f_null", "f_chair", "f_rubble", "f_chair" ],
        "c": [ "f_counter", "f_null", "f_null", "f_null", "f_null", "f_null", "f_null", "f_counter", "f_rubble", "f_counter" ],
        "&": [ "f_trashcan", "f_null", "f_null", "f_null", "f_null", "f_null", "f_null", "f_trashcan", "f_rubble", "f_trashcan" ]
      },
      "toilets": { "P": {  } },
      "//": "Default fill is floor but some tables are outside",
      "set": [
        { "line": "terrain", "x": 21, "y": 2, "x2": 18, "y2": 2, "id": "t_concrete" },
        { "line": "terrain", "x": 21, "y": 8, "x2": 18, "y2": 8, "id": "t_concrete" },
        { "line": "terrain", "x": 21, "y": 6, "x2": 21, "y2": 4, "id": "t_concrete" },
        { "line": "terrain", "x": 18, "y": 6, "x2": 18, "y2": 4, "id": "t_concrete" }
      ]
    }
  }
]
