[
  {
    "type": "mapgen",
    "om_terrain": [ "s_restaurant" ],
    "method": "json",
    "weight": "300 g",
    "object": {
      "fill_ter": "t_linoleum_white",
      "rows": [
        "____,____,____,____,____",
        "____,____,____,____,____",
        "____,____,____,____,____",
        "____,____,____,____,____",
        "____,____,____,____,____",
        "========================",
        "=|OOOOOOOOOOOOOOO--+--|=",
        "=|HtHHtHHtHHtHHtHlblbl|=",
        "=|HtHHtHHtHHtHHtHblblb|=",
        "=|blblblblblblblblblbl|=",
        "=|cbcbcbcbcbcbcbcbcblb|=",
        "=|#################lbl|=",
        "=|lblblblblblblblb#blb|=",
        "=|blblblblblblblblblbl|=",
        "=|lb####ffGGGG####lblb|=",
        "=|bl-------------|--+-|=",
        "=|lb###fffffff###|llll|=",
        "=|blblblblblblblb|llll|=",
        "=|lblblblblblblbl|lSTl|=",
        "=|---------------|----|=",
        "========================",
        "........................",
        "........................",
        "........................"
      ],
      "terrain": {
        "O": [
          "t_window",
          "t_window_taped",
          "t_window",
          "t_window_empty",
          "t_window",
          "t_window_frame",
          "t_window",
          "t_wall_wood",
          "t_window",
          "t_wall_wood_chipped",
          "t_window",
          "t_wall_wood_broken",
          "t_window",
          "t_wall_log",
          "t_window",
          "t_wall_log_chipped",
          "t_window",
          "t_wall_log_broken"
        ],
        "+": [
          "t_door_c",
          "t_door_c",
          "t_door_locked_alarm",
          "t_door_c",
          "t_door_c",
          "t_door_locked_interior",
          "t_door_c",
          "t_door_c",
          "t_door_locked",
          "t_door_c",
          "t_door_c",
          "t_door_locked_peep",
          "t_door_c",
          "t_door_c",
          "t_door_b_peep",
          "t_door_c",
          "t_door_c",
          "t_door_boarded_damaged_peep",
          "t_door_c",
          "t_door_c",
          "t_rdoor_boarded_damaged",
          "t_door_c",
          "t_door_c",
          "t_rdoor_boarded",
          "t_door_c",
          "t_door_c",
          "t_door_boarded_peep",
          "t_door_c",
          "t_door_c",
          "t_door_boarded_damaged",
          "t_door_c",
          "t_door_c",
          "t_door_boarded",
          "t_door_c",
          "t_door_c",
          "t_rdoor_o",
          "t_door_c",
          "t_door_c",
          "t_rdoor_c",
          "t_door_c",
          "t_door_c",
          "t_door_o_peep",
          "t_door_c",
          "t_door_c",
          "t_door_c_peep",
          "t_door_c",
          "t_door_c",
          "t_door_b",
          "t_door_c",
          "t_door_c",
          "t_door_frame",
          "t_door_c",
          "t_door_c",
          "t_wall_wood",
          "t_door_c",
          "t_door_c",
          "t_wall_wood_chipped",
          "t_door_c",
          "t_door_c",
          "t_wall_wood_broken",
          "t_door_o",
          "t_door_o",
          "t_wall_log",
          "t_door_o",
          "t_door_o",
          "t_wall_log_chipped",
          "t_door_o",
          "t_door_o",
          "t_wall_log_broken",
          "t_door_o",
          "t_door_o",
          "t_door_curtain_c",
          "t_door_o",
          "t_door_o",
          "t_door_makeshift_c",
          "t_door_o",
          "t_door_o",
          "t_door_curtain_o",
          "t_door_o",
          "t_door_o",
          "t_door_makeshift_o",
          "t_door_o",
          "t_door_o",
          "t_palisade",
          "t_door_o",
          "t_door_o",
          "t_bars",
          "t_door_o",
          "t_door_o",
          "t_door_bar_o",
          "t_door_o",
          "t_door_o",
          "t_door_bar_c",
          "t_door_o",
          "t_door_o",
          "t_door_bar_locked"
        ],
        ".": [ "t_grass", "t_grass", "t_grass", "t_grass", "t_grass", "t_grass", "t_dirt" ],
        "_": "t_pavement",
        ",": "t_pavement_y",
        "-": "t_wall",
        "|": "t_wall",
        "c": "t_linoleum_white",
        "#": "t_linoleum_gray",
        "t": "t_linoleum_gray",
        "T": "t_linoleum_white",
        "=": "t_sidewalk",
        "G": "t_linoleum_gray",
        "f": "t_linoleum_white",
        "S": "t_linoleum_white",
        "H": "t_linoleum_white",
        "l": "t_linoleum_white",
        "b": "t_linoleum_gray"
      },
      "furniture": {
        "#": [ "f_counter", "f_null", "f_null", "f_null", "f_null", "f_null", "f_null", "f_counter", "f_rubble", "f_counter" ],
        "t": [ "f_table", "f_null", "f_null", "f_null", "f_null", "f_null", "f_null", "f_table", "f_rubble", "f_table" ],
        "S": [ "f_sink", "f_null", "f_null", "f_null", "f_null", "f_null", "f_null", "f_sink", "f_rubble", "f_sink" ],
        "G": [ "f_oven", "f_null", "f_null", "f_null", "f_null", "f_null", "f_null", "f_oven", "f_wreckage", "f_oven" ],
        "f": [ "f_fridge", "f_null", "f_null", "f_null", "f_null", "f_null", "f_null", "f_fridge", "f_wreckage", "f_fridge" ],
        "H": [ "f_sofa", "f_null", "f_null", "f_null", "f_null", "f_null", "f_null", "f_sofa", "f_rubble", "f_sofa" ]
      },
      "toilets": { "T": {  } }
    }
  }
]
