[
  {
    "type": "mapgen",
    "om_terrain": [ "pump_station_1" ],
    "method": "json",
    "weight": 250,
    "object": {
      "fill_ter": "t_floor",
      "rows": [
        "sss___________sss.......",
        ".ss___________ss|-w-w-|.",
        ".ss___________ss|rrr L|.",
        ".ss___________ss;    Lw.",
        ".ss___________ss|    c|.",
        ".ss_____}_____ss|    c|.",
        ".ss___________ssw    cw.",
        ".ss___________ss|    c|.",
        ".ss___________ss|    c|.",
        ".ss___________sswr   Lw.",
        ".ss___________ss|r   L|.",
        ".sss_________sss|| |--|.",
        ".ssssssssssssssss| |rr|.",
        "..sssssssssssssss| |  w.",
        "...|-w-w-|s|-w-|s| |  |.",
        "...| k6  |s|hhh|s| | 3|.",
        "...| hk h|s+   |s|   3w.",
        "...|o k  |s|   |s| | 3|.",
        "...|o    |s|6c |s| |  |.",
        "...|---+-|s|ch |s| |  w.",
        "...|rr|  |s|c  |s| |rr|.",
        "...|  *  |s|  P|s| |--|.",
        "...|rr|  |s|---|s|    |.",
        "...|--|  |ssssssz|    w."
      ],
      "terrain": {
        "|": "t_wall",
        "-": "t_wall",
        ".": [ "t_grass", "t_grass", "t_grass", "t_grass", "t_grass", "t_grass", "t_dirt" ],
        "3": "t_recycler",
        "6": "t_console_broken",
        "_": "t_pavement",
        "+": [
          "t_door_c",
          "t_door_c",
          "t_door_locked_alarm",
          "t_door_c",
          "t_door_c",
          "t_door_locked_interior",
          "t_door_c",
          "t_door_c",
          "t_door_locked",
          "t_door_c",
          "t_door_c",
          "t_door_locked_peep",
          "t_door_c",
          "t_door_c",
          "t_door_b_peep",
          "t_door_c",
          "t_door_c",
          "t_door_boarded_damaged_peep",
          "t_door_c",
          "t_door_c",
          "t_rdoor_boarded_damaged",
          "t_door_c",
          "t_door_c",
          "t_rdoor_boarded",
          "t_door_c",
          "t_door_c",
          "t_door_boarded_peep",
          "t_door_c",
          "t_door_c",
          "t_door_boarded_damaged",
          "t_door_c",
          "t_door_c",
          "t_door_boarded",
          "t_door_c",
          "t_door_c",
          "t_rdoor_o",
          "t_door_c",
          "t_door_c",
          "t_rdoor_c",
          "t_door_c",
          "t_door_c",
          "t_door_o_peep",
          "t_door_c",
          "t_door_c",
          "t_door_c_peep",
          "t_door_c",
          "t_door_c",
          "t_door_b",
          "t_door_c",
          "t_door_c",
          "t_door_frame",
          "t_door_c",
          "t_door_c",
          "t_wall_wood",
          "t_door_c",
          "t_door_c",
          "t_wall_wood_chipped",
          "t_door_c",
          "t_door_c",
          "t_wall_wood_broken",
          "t_door_o",
          "t_door_o",
          "t_wall_log",
          "t_door_o",
          "t_door_o",
          "t_wall_log_chipped",
          "t_door_o",
          "t_door_o",
          "t_wall_log_broken",
          "t_door_o",
          "t_door_o",
          "t_door_curtain_c",
          "t_door_o",
          "t_door_o",
          "t_door_makeshift_c",
          "t_door_o",
          "t_door_o",
          "t_door_curtain_o",
          "t_door_o",
          "t_door_o",
          "t_door_makeshift_o",
          "t_door_o",
          "t_door_o",
          "t_palisade",
          "t_door_o",
          "t_door_o",
          "t_bars",
          "t_door_o",
          "t_door_o",
          "t_door_bar_o",
          "t_door_o",
          "t_door_o",
          "t_door_bar_c",
          "t_door_o",
          "t_door_o",
          "t_door_bar_locked"
        ],
        ";": [
          "t_door_c",
          "t_door_c",
          "t_door_b",
          "t_door_c",
          "t_door_c",
          "t_door_frame",
          "t_door_c",
          "t_door_c",
          "t_wall_wood",
          "t_door_c",
          "t_door_c",
          "t_wall_wood_chipped",
          "t_door_c",
          "t_door_c",
          "t_wall_wood_broken",
          "t_door_o",
          "t_door_o",
          "t_wall_log",
          "t_door_o",
          "t_door_o",
          "t_wall_log_chipped",
          "t_door_o",
          "t_door_o",
          "t_wall_log_broken"
        ],
        "*": [
          "t_door_bar_c",
          "t_door_bar_c",
          "t_door_b",
          "t_door_bar_c",
          "t_door_bar_c",
          "t_door_frame",
          "t_door_bar_c",
          "t_door_bar_c",
          "t_wall_wood",
          "t_door_bar_c",
          "t_door_bar_c",
          "t_wall_wood_chipped",
          "t_door_bar_c",
          "t_door_bar_c",
          "t_wall_wood_broken",
          "t_door_bar_o",
          "t_door_bar_o",
          "t_wall_log",
          "t_door_bar_o",
          "t_door_bar_o",
          "t_wall_log_chipped",
          "t_door_bar_o",
          "t_door_bar_o",
          "t_wall_log_broken"
        ],
        "}": "t_manhole_cover",
        "c": "t_floor",
        "h": "t_floor",
        "k": "t_floor",
        "L": "t_floor",
        "o": "t_floor",
        "P": "t_floor",
        "r": "t_floor",
        "s": "t_sidewalk",
        "w": [
          "t_window",
          "t_window_taped",
          "t_window",
          "t_window_empty",
          "t_window",
          "t_window_frame",
          "t_window",
          "t_wall_wood",
          "t_window",
          "t_wall_wood_chipped",
          "t_window",
          "t_wall_wood_broken",
          "t_window",
          "t_wall_log",
          "t_window",
          "t_wall_log_chipped",
          "t_window",
          "t_wall_log_broken"
        ],
        "z": "t_sidewalk"
      },
      "furniture": {
        "c": [ "f_counter", "f_null", "f_null", "f_null", "f_null", "f_null", "f_null", "f_counter", "f_rubble", "f_counter" ],
        "h": [ "f_chair", "f_null", "f_null", "f_null", "f_null", "f_null", "f_null", "f_chair", "f_rubble", "f_chair" ],
        "k": [ "f_desk", "f_null", "f_null", "f_null", "f_null", "f_null", "f_null", "f_desk", "f_rubble", "f_desk" ],
        "L": [ "f_locker", "f_null", "f_null", "f_null", "f_null", "f_null", "f_null", "f_locker", "f_wreckage", "f_locker" ],
        "o": [ "f_bookcase", "f_null", "f_null", "f_null", "f_null", "f_null", "f_null", "f_bookcase", "f_rubble", "f_bookcase" ],
        "P": [ "f_indoor_plant", "f_null", "f_null", "f_null", "f_null", "f_null", "f_null", "f_null" ],
        "r": [ "f_rack", "f_null", "f_null", "f_null", "f_null", "f_null", "f_null", "f_rack", "f_rubble", "f_rack" ],
        "z": [ "f_crate_c", "f_null", "f_null", "f_null", "f_null", "f_null", "f_null", "f_crate_c", "f_rubble", "f_crate_c" ]
      },
      "set": [
        { "point": "terrain", "id": "t_dirt", "x": [ 23, 23 ], "y": [ 0, 23 ], "repeat": [ 6, 10 ] },
        { "point": "terrain", "id": "t_dirt", "x": [ 0, 2 ], "y": [ 14, 23 ], "repeat": [ 8, 15 ] }
      ],
      "place_monsters": [ { "monster": "GROUP_ZOMBIE", "chance": 3, "x": [ 5, 21 ], "y": [ 8, 23 ] } ]
    }
  },
  {
    "type": "mapgen",
    "om_terrain": [ "pump_station_2" ],
    "method": "json",
    "weight": 250,
    "object": {
      "fill_ter": "t_floor",
      "rows": [
        "...|rr|  |ssssszz|  11|.",
        "...|  *  |sszzssz|  11|.",
        "...|rr|  |sszzsss|   2w.",
        "...|--|  |-------|  11|.",
        "...|rr|   rrrr      11|.",
        "...|  *              2w.",
        "...|rr|              2|.",
        "...|--|              2|.",
        "...|rr7              2w.",
        "...|  9  44 44 44 44 2|.",
        "...w  7  4424424424422|.",
        "...| }7              rw.",
        "...|  7              r|.",
        "...|rr7r  LL        rr|.",
        "...|----w----w--w--w--|.",
        "........................",
        "........................",
        "........................",
        "........................",
        "........................",
        "........................",
        "........................",
        "........................",
        "........................"
      ],
      "terrain": {
        "|": "t_wall",
        "-": "t_wall",
        ".": [ "t_grass", "t_grass", "t_grass", "t_grass", "t_grass", "t_grass", "t_dirt" ],
        "1": "t_generator_broken",
        "2": "t_sewage_pipe",
        "4": "t_water_pump",
        "7": "t_chainfence_h",
        "9": [ "t_chaingate_c", "t_chaingate_c", "t_chaingate_c", "t_chaingate_o" ],
        "*": [
          "t_door_bar_c",
          "t_door_bar_c",
          "t_door_b",
          "t_door_bar_c",
          "t_door_bar_c",
          "t_door_frame",
          "t_door_bar_c",
          "t_door_bar_c",
          "t_wall_wood",
          "t_door_bar_c",
          "t_door_bar_c",
          "t_wall_wood_chipped",
          "t_door_bar_c",
          "t_door_bar_c",
          "t_wall_wood_broken",
          "t_door_bar_o",
          "t_door_bar_o",
          "t_wall_log",
          "t_door_bar_o",
          "t_door_bar_o",
          "t_wall_log_chipped",
          "t_door_bar_o",
          "t_door_bar_o",
          "t_wall_log_broken"
        ],
        "}": "t_manhole_cover",
        "L": "t_floor",
        "r": "t_floor",
        "s": "t_sidewalk",
        "w": [
          "t_window",
          "t_window_taped",
          "t_window",
          "t_window_empty",
          "t_window",
          "t_window_frame",
          "t_window",
          "t_wall_wood",
          "t_window",
          "t_wall_wood_chipped",
          "t_window",
          "t_wall_wood_broken",
          "t_window",
          "t_wall_log",
          "t_window",
          "t_wall_log_chipped",
          "t_window",
          "t_wall_log_broken"
        ],
        "z": "t_sidewalk"
      },
      "furniture": {
        "L": [ "f_locker", "f_null", "f_null", "f_null", "f_null", "f_null", "f_null", "f_locker", "f_wreckage", "f_locker" ],
        "r": [ "f_rack", "f_null", "f_null", "f_null", "f_null", "f_null", "f_null", "f_rack", "f_rubble", "f_rack" ],
        "z": [ "f_crate_c", "f_null", "f_null", "f_null", "f_null", "f_null", "f_null", "f_crate_c", "f_rubble", "f_crate_c" ]
      },
      "set": [
        { "point": "terrain", "id": "t_dirt", "x": [ 23, 23 ], "y": [ 0, 23 ], "repeat": [ 6, 10 ] },
        { "point": "terrain", "id": "t_dirt", "x": [ 3, 22 ], "y": [ 15, 23 ], "repeat": [ 40, 90 ] },
        { "point": "terrain", "id": "t_dirt", "x": [ 0, 2 ], "y": [ 0, 23 ], "repeat": [ 15, 30 ] }
      ],
      "place_monsters": [ { "monster": "GROUP_ZOMBIE", "chance": 3, "x": [ 4, 21 ], "y": [ 0, 13 ] } ]
    }
  },
  {
    "type": "mapgen",
    "om_terrain": [ "pump_station_3" ],
    "method": "json",
    "weight": 250,
    "object": {
      "fill_ter": "t_rock_floor",
      "rows": [
        "RRRRRRRRRRRRRRRRRRRRRRRR",
        "RRRRRRRRRRRRRRRRRRRRRRRR",
        "RRRRRRRRRRRRRRRRRRRRRRRR",
        "RRRRRRRRRRRRRRRRRRRRRRRR",
        "RRRRRRRRRRRRRRRRRRRRRRRR",
        "RRRRRRRRRRRRRRRRRRRRRRRR",
        "RRRRRRRRRRRRRRRRRRRRRRRR",
        "RRRRRRRRRRRRRRRRRRRRRRRR",
        "RRRRRRRRRRRRRRRRRRRRRRRR",
        "R222222RRRRRRRRRRRRRRRRR",
        "!xa~~x2~~~~~~x!~~~~~~~~~",
        "!xa~~x2~~~~~~x!~~~~~~~~~",
        "!xaA~x2~~~~~~x!~~~~~~~~~",
        "!xxxxxxxxxxxxx!~~~~~~~~~",
        "RRRR~x2RRRRRRRRRRRRRRRRR",
        "RRRR~x2RRRRRRRRRRRRRRRRR",
        "RRRR~x2RRRRRRRRRRRRRRRRR",
        "RRRR~x2RRRRRRRRRRRRRRRRR",
        "RRRR~x2RRRRRRRRRRRRRRRRR",
        "RRRR~x2RRRRRRRRRRRRRRRRR",
        "RRRR~x2RRRRRRRRRRRRRRRRR",
        "RRRR~x2RRRRRRRRRRRRRRRRR",
        "RRRR~x2RRRRRRRRRRRRRRRRR",
        "RRRR~x2RRRRRRRRRRRRRRRRR"
      ],
      "terrain": {
        "2": "t_sewage_pipe",
        "~": "t_sewage",
        "!": "t_bars",
        "A": "t_railing_h",
        "a": "t_railing_v",
        "R": "t_rock",
        "x": "t_bridge"
      },
      "place_monsters": [ { "monster": "GROUP_SEWER", "x": [ 1, 22 ], "y": [ 1, 22 ], "density": 0.1 } ]
    }
  },
  {
    "type": "mapgen",
    "om_terrain": [ "pump_station_4" ],
    "method": "json",
    "weight": 250,
    "object": {
      "fill_ter": "t_rock_floor",
      "rows": [
        "RRRR~x2RRRRRRRRRRRRRRRRR",
        "RRRR~x2RRRRRRRRRRRRRRRRR",
        "RRRR~x2RRRRRRRRRRRRRRRRR",
        "RRRR~x2RRRRRRRRRRRRRRRRR",
        "RRRR~x2   RRRRRRRRRRRRRR",
        "RRRR~xxx^ RRRRRRRRRRRRRR",
        "RRRR~x2   RRRRRRRRRRRRRR",
        "RRRR~x2RRRRRRRRRRRRRRRRR",
        "RRRR~x2RRRRRRRRRRRRRRRRR",
        "RRRR~x2RRRRRRRRRRRRRRRRR",
        "RRRR~x2RRRRRRRRRRRRRRRRR",
        "RRRR~x2RRRRRRRRRRRRRRRRR",
        "RRRR~x2RRRRRRRRRRRRRRRRR",
        "RRRR~x2RRRRRRRRRRRRRRRRR",
        "RRRR~x2RRRRRRRRRRRRRRRRR",
        "RRRR~x2RRRRRRRRRRRRRRRRR",
        "RRRR~x2RRRRRRRRRRRRRRRRR",
        "RRRR~x2RRRRRRRRRRRRRRRRR",
        "RRRR~x2RRRRRRRRRRRRRRRRR",
        "RRRR~x2RRRRRRRRRRRRRRRRR",
        "RRRR~x2RRRRRRRRRRRRRRRRR",
        "RRRR~x2RRRRRRRRRRRRRRRRR",
        "RRRR~x2RRRRRRRRRRRRRRRRR",
        "RRRR~x2RRRRRRRRRRRRRRRRR"
      ],
      "terrain": { "2": "t_sewage_pipe", "~": "t_sewage", "^": "t_ladder_up", "x": "t_bridge", "R": "t_rock" },
      "place_monsters": [ { "monster": "GROUP_SEWER", "x": [ 1, 22 ], "y": [ 1, 22 ], "density": 0.1 } ]
    }
  },
  {
    "type": "mapgen",
    "om_terrain": [ "pump_station_5" ],
    "method": "json",
    "weight": 250,
    "object": {
      "fill_ter": "t_rock_floor",
      "rows": [
        "RRRR~x2RRRRRRRRRRRRRRRRR",
        "RRRR~x2RRRRRRRRRRRRRRRRR",
        "RRRR~x2RRRRRRRRRRRRRRRRR",
        "RRRR~x2RRRRRRRRRRRRRRRRR",
        "RRRR~x2RRRRRRRRRRRRRRRRR",
        "RRRR~x2RRRRRRRRRRRRRRRRR",
        "RRRR!*2RRRRRRRRRRRRRRRRR",
        "RRRR~x2RRRRRRRRRRRRRRRRR",
        "RRRR~x2RRRRRRRRRRRRRRRRR",
        "RR~~~x2RRRRRRRRRRRRRRRRR",
        "R~~~~x22222222222 RRRRRR",
        "!~~~axx   2  2  2 RRRRRR",
        "!~~~a^x           RRRRRR",
        "!~~~axx           RRRRRR",
        "!~~~aAAR   RRRRRRRRRRRRR",
        "R~~~~~~Rc LRRRRRRRRRRRRR",
        "RRRRRRRRc LRRRRRRRRRRRRR",
        "RRRRRRRRR RRRRRRRRRRRRRR",
        "RRRRRRRRRRRRRRRRRRRRRRRR",
        "RRRRRRRRRRRRRRRRRRRRRRRR",
        "RRRRRRRRRRRRRRRRRRRRRRRR",
        "RRRRRRRRRRRRRRRRRRRRRRRR",
        "RRRRRRRRRRRRRRRRRRRRRRRR",
        "RRRRRRRRRRRRRRRRRRRRRRRR"
      ],
      "terrain": {
        "2": "t_sewage_pipe",
        "~": "t_sewage",
        "^": "t_ladder_up",
        "!": "t_bars",
        "*": [
          "t_door_bar_c",
          "t_door_bar_c",
          "t_door_b",
          "t_door_bar_c",
          "t_door_bar_c",
          "t_door_frame",
          "t_door_bar_c",
          "t_door_bar_c",
          "t_wall_wood",
          "t_door_bar_c",
          "t_door_bar_c",
          "t_wall_wood_chipped",
          "t_door_bar_c",
          "t_door_bar_c",
          "t_wall_wood_broken",
          "t_door_bar_o",
          "t_door_bar_o",
          "t_wall_log",
          "t_door_bar_o",
          "t_door_bar_o",
          "t_wall_log_chipped",
          "t_door_bar_o",
          "t_door_bar_o",
          "t_wall_log_broken"
        ],
        "A": "t_railing_h",
        "a": "t_railing_v",
        "c": "t_rock_floor",
        "L": "t_rock_floor",
        "R": "t_rock",
        "x": "t_bridge"
      },
      "furniture": {
        "c": [ "f_counter", "f_null", "f_null", "f_null", "f_null", "f_null", "f_null", "f_counter", "f_rubble", "f_counter" ],
        "L": [ "f_locker", "f_null", "f_null", "f_null", "f_null", "f_null", "f_null", "f_locker", "f_wreckage", "f_locker" ]
      },
      "place_monsters": [ { "monster": "GROUP_SEWER", "x": [ 1, 22 ], "y": [ 1, 22 ], "density": 0.1 } ]
    }
  }
]
