[
  {   "type" : "AMMO",
        "id" : "seed_sunflower",
        "category": "other",
        "price" : 120,
        "name" : "sunflower seeds",
        "symbol" : ".",
        "color" : "brown",
        "description" : "a pack of sun flower seeds",
        "material" : "fruit",
        "volume" : 1,
        "weight" : 1,
        "bashing" : 0,
        "cutting" : 0,
        "to_hit" : 0,
        "ammo_type" : "NULL",
        "damage" : 0,
        "pierce" : 0,
        "range" : 0,
        "dispersion" : 0,
        "recoil" : 0,
        "count" : 4
    },
    {
    "type":"GENERIC",
    "id": "l_pointer",
    "symbol":"!",
    "color": "green",
    "name": "laser pointer",
    "description": "A green laser pointer",
    "price": 4,
    "material": ["plastic", "null"],
    "weight": 5,
    "volume": 1,
    "bashing": 1,
    "cutting": 0,
    "to_hit": 0
    },
    { "type":"GENERIC",
    "id": "lc_sword",
    "symbol" : "!",
    "color": "dark_gray",
    "name": "Light Calvary Sword",
    "description": "used by US cavalry from the American Civil War until the end of the Indian wars; some were still in use during the Spanish-American War.It was 41in long with a 35in by 1in blade and weighed 2 lb 4oz alone or 3 lb 10oz with iron scabbard.",
    "material": "steel",
    "price": 0,
    "volume": 8,
    "weight": 550,
    "bashing": 3,
    "cutting": 16,
    "to_hit": 2,
    "techniques": ["WBLOCK_2"]
    },
    { "type":"GENERIC",
    "id": "g_spear",
    "symbol" : "!",
    "color": "blue",
    "name": "Glass Shard Spear",
    "description": "a piece of glass taped to a pipe for a basic stabbing weapon",
    "material": ["steel","glass"],
    "price": 0,
    "volume": 6,
    "weight": 430,
    "bashing": 2,
    "cutting": 8,
    "to_hit": 2,
    "flags" : ["STAB"]
    },
    {   "type" : "AMMO",
        "id" : "r_paint",
        "category": "other",
        "price" : 120,
        "name" : "red paint",
        "symbol" : "o",
        "color" : "red",
        "description" : "a can of red paint",
        "material" : "steel",
        "volume" : 5,
        "weight" : 10,
        "bashing" : 0,
        "cutting" : 0,
        "to_hit" : 0,
        "ammo_type" : "NULL",
        "damage" : 0,
        "pierce" : 0,
        "range" : 0,
        "dispersion" : 0,
        "recoil" : 0,
        "count" : 100
    },
    {   "type" : "AMMO",
        "id" : "b_paint",
        "category": "other",
        "price" : 120,
        "name" : "blue paint",
        "symbol" : "o",
        "color" : "blue",
        "description" : "a can of blue paint",
        "material" : "steel",
        "volume" : 5,
        "weight" : 10,
        "bashing" : 0,
        "cutting" : 0,
        "to_hit" : 0,
        "ammo_type" : "NULL",
        "damage" : 0,
        "pierce" : 0,
        "range" : 0,
        "dispersion" : 0,
        "recoil" : 0,
        "count" : 100
    },
    {   "type" : "AMMO",
        "id" : "w_paint",
        "category": "other",
        "price" : 120,
        "name" : "white paint",
        "symbol" : "o",
        "color" : "white",
        "description" : "a can of white paint",
        "material" : "steel",
        "volume" : 5,
        "weight" : 10,
        "bashing" : 0,
        "cutting" : 0,
        "to_hit" : 0,
        "ammo_type" : "NULL",
        "damage" : 0,
        "pierce" : 0,
        "range" : 0,
        "dispersion" : 0,
        "recoil" : 0,
        "count" : 100
    },
    {   "type" : "AMMO",
        "id" : "g_paint",
        "category": "other",
        "price" : 120,
        "name" : "green paint",
        "symbol" : "o",
        "color" : "green",
        "description" : "a can of green paint",
        "material" : "steel",
        "volume" : 5,
        "weight" : 10,
        "bashing" : 0,
        "cutting" : 0,
        "to_hit" : 0,
        "ammo_type" : "NULL",
        "damage" : 0,
        "pierce" : 0,
        "range" : 0,
        "dispersion" : 0,
        "recoil" : 0,
        "count" : 100
    },
    {   "type" : "AMMO",
        "id" : "p_paint",
        "category": "other",
        "price" : 120,
        "name" : "purple paint",
        "symbol" : "o",
        "color" : "magenta",
        "description" : "a can of purple paint",
        "material" : "steel",
        "volume" : 5,
        "weight" : 10,
        "bashing" : 0,
        "cutting" : 0,
        "to_hit" : 0,
        "ammo_type" : "NULL",
        "damage" : 0,
        "pierce" : 0,
        "range" : 0,
        "dispersion" : 0,
        "recoil" : 0,
        "count" : 100
    },
    {   "type" : "AMMO",
        "id" : "y_paint",
        "category": "other",
        "price" : 120,
        "name" : "yellow paint",
        "symbol" : "o",
        "color" : "yellow",
        "description" : "a can of yellow paint",
        "material" : "steel",
        "volume" : 5,
        "weight" : 10,
        "bashing" : 0,
        "cutting" : 0,
        "to_hit" : 0,
        "ammo_type" : "NULL",
        "damage" : 0,
        "pierce" : 0,
        "range" : 0,
        "dispersion" : 0,
        "recoil" : 0,
        "count" : 100
    },
    {   "type" : "AMMO",
        "id" : "r_carpet",
        "category": "other",
        "price" : 120,
        "name" : "red carpet",
        "symbol" : "}",
        "color" : "red",
        "description" : "a roll of red carpet",
        "material" : "steel",
        "volume" : 7,
        "weight" : 45,
        "bashing" : 0,
        "cutting" : 0,
        "to_hit" : 0,
        "ammo_type" : "NULL",
        "damage" : 0,
        "pierce" : 0,
        "range" : 0,
        "dispersion" : 0,
        "recoil" : 0,
        "count" : 5
    },
    {   "type" : "AMMO",
        "id" : "g_carpet",
        "category": "other",
        "price" : 120,
        "name" : "green carpet",
        "symbol" : "}",
        "color" : "green",
        "description" : "a roll of green carpet",
        "material" : "steel",
        "volume" : 7,
        "weight" : 45,
        "bashing" : 0,
        "cutting" : 0,
        "to_hit" : 0,
        "ammo_type" : "NULL",
        "damage" : 0,
        "pierce" : 0,
        "range" : 0,
        "dispersion" : 0,
        "recoil" : 0,
        "count" : 5
    },
    {   "type" : "AMMO",
        "id" : "y_carpet",
        "category": "other",
        "price" : 120,
        "name" : "yellow carpet",
        "symbol" : "}",
        "color" : "yellow",
        "description" : "a roll of yellow carpet",
        "material" : "steel",
        "volume" : 7,
        "weight" : 45,
        "bashing" : 0,
        "cutting" : 0,
        "to_hit" : 0,
        "ammo_type" : "NULL",
        "damage" : 0,
        "pierce" : 0,
        "range" : 0,
        "dispersion" : 0,
        "recoil" : 0,
        "count" : 5
    },
    {   "type" : "AMMO",
        "id" : "p_carpet",
        "category": "other",
        "price" : 120,
        "name" : "purple carpet",
        "symbol" : "}",
        "color" : "magenta",
        "description" : "a roll of purple carpet",
        "material" : "steel",
        "volume" : 7,
        "weight" : 45,
        "bashing" : 0,
        "cutting" : 0,
        "to_hit" : 0,
        "ammo_type" : "NULL",
        "damage" : 0,
        "pierce" : 0,
        "range" : 0,
        "dispersion" : 0,
        "recoil" : 0,
        "count" : 5
    },
    {
    "id": "chipper",
    "type": "TOOL",
    "symbol": ";",
    "color": "brown",
    "name": "paint chipper",
    "description": "A chisel type tool used to take the paint off things",
    "price": 7000,
    "material": ["steel", "wood"],
    "weight": 60,
    "volume": 2,
    "bashing": 0,
    "cutting": 2,
    "to_hit": 1,
    "max_charges": 0,
    "initial_charges": 0,
    "charges_per_use": 0,
    "turns_per_charge": 0,
    "ammo": "NULL",
    "revert_to": "null",
    "use_action": "NONE"
   },
   {
    "id": "paint_brush",
    "type": "TOOL",
    "symbol": ";",
    "color": "brown",
    "name": "paint brush",
    "description": "A brush used for painting things",
    "price": 7000,
    "material": ["steel", "wood"],
    "weight": 60,
    "volume": 2,
    "bashing": 0,
    "cutting": 0,
    "to_hit": 1,
    "max_charges": 0,
    "initial_charges": 0,
    "charges_per_use": 0,
    "turns_per_charge": 0,
    "ammo": "NULL",
    "revert_to": "null",
    "use_action": "NONE"
   }
]


