[
  {
    "type": "GENERIC",
    "id": "dildo_bat",
    "symbol": ")",
    "color": "purple",
    "name": { "str": "Dildo Bat", "str_pl": "dildo_bats" },
    "description": "A comicly large purple dildo about a metre in length. You faintly see 'The absurdity of a sex toy with the lethality of a baseball bat.' engrave on the handle.",
    "price": 4000,
    "material": "plastic",
    "techniques": [ "WBLOCK_1", "BRUTAL" ],
    "flags": [ "DURABLE_MELEE", "NONCONDUCTIVE" ],
    "weight": 2000,
    "volume": 12,
    "bashing": 21,
    "category": "weapons",
    "to_hit": 2
  },
  {
    "type": "GENERIC",
    "id": "small_whip",
    "symbol": "/",
    "color": "brown",
    "name": { "str": "Small Leather Whip", "str_pl": "small_whips" },
    "description": "Small leather whip. Typically used in BDSM and foreplay. Not much use as a weapon.",
    "price": 400,
    "material": "leather",
    "weight": 200,
    "volume": 3,
    "cutting": 5,
    "category": "weapons",
    "to_hit": -1
  }
]
